{
  "murder": {
    "precinct": "10",
    "crime": {
      "name": "Murder",
      "penal": "A-1",
      "classification": "FELONY",
      "number": 37
    },
    "week": {
      "2015": "0",
      "2016": "0",
      "change": "***.*"
    },
    "28day": {
      "2015": "0",
      "2016": "0",
      "change": "***.*"
    },
    "year": {
      "2015": "0",
      "2016": "0",
      "change": "***.*"
    },
    "2year": {
      "change": "***.*"
    },
    "6year": {
      "change": "***.*"
    },
    "23year": {
      "change": "***.*"
    }
  },
  "rape": {
    "precinct": "10",
    "crime": {
      "name": "Rape",
      "penal": [
        "E",
        "D",
        "B"
      ],
      "classification": "FELONY",
      "number": 50
    },
    "week": {
      "2015": "0",
      "2016": "0",
      "change": "***.*"
    },
    "28day": {
      "2015": "0",
      "2016": "0",
      "change": "***.*"
    },
    "year": {
      "2015": "0",
      "2016": "0",
      "change": "***.*"
    },
    "2year": {
      "change": "-100.0"
    },
    "6year": {
      "change": "***.*"
    },
    "23year": {
      "change": "-100.0"
    }
  },
  "robbery": {
    "precinct": "10",
    "crime": {
      "name": "Robbery",
      "penal": [
        "D",
        "C",
        "B"
      ],
      "classification": "FELONY",
      "number": 63
    },
    "week": {
      "2015": "2",
      "2016": "1",
      "change": "-50.0"
    },
    "28day": {
      "2015": "8",
      "2016": "11",
      "change": "37.5"
    },
    "year": {
      "2015": "3",
      "2016": "2",
      "change": "-33.3"
    },
    "2year": {
      "change": "100.0"
    },
    "6year": {
      "change": "-33.3"
    },
    "23year": {
      "change": "-84.6"
    }
  },
  "felAssault": {
    "precinct": "10",
    "crime": {
      "name": "Felonious Assault",
      "penal": [
        "D",
        "B"
      ],
      "classification": "FELONY",
      "number": 76
    },
    "week": {
      "2015": "2",
      "2016": "4",
      "change": "100.0"
    },
    "28day": {
      "2015": "8",
      "2016": "11",
      "change": "37.5"
    },
    "year": {
      "2015": "2",
      "2016": "6",
      "change": "200.0"
    },
    "2year": {
      "change": "50.0"
    },
    "6year": {
      "change": "50.0"
    },
    "23year": {
      "change": "20.0"
    }
  },
  "burglary": {
    "precinct": "10",
    "crime": {
      "name": "Burglary",
      "penal": [
        "D",
        "C",
        "B"
      ],
      "classification": "FELONY",
      "number": 89
    },
    "week": {
      "2015": "2",
      "2016": "2",
      "change": "0.0"
    },
    "28day": {
      "2015": "7",
      "2016": "6",
      "change": "-14.3"
    },
    "year": {
      "2015": "2",
      "2016": "3",
      "change": "50.0"
    },
    "2year": {
      "change": "50.0"
    },
    "6year": {
      "change": "50.0"
    },
    "23year": {
      "change": "-40.0"
    }
  },
  "grandLarceny": {
    "precinct": "10",
    "crime": {
      "name": "Grand Larceny",
      "penal": [
        "E",
        "D",
        "C",
        "B"
      ],
      "classification": "FELONY",
      "number": 102
    },
    "week": {
      "2015": "9",
      "2016": "6",
      "change": "-33.3"
    },
    "28day": {
      "2015": "41",
      "2016": "44",
      "change": "7.3"
    },
    "year": {
      "2015": "11",
      "2016": "9",
      "change": "-18.2"
    },
    "2year": {
      "change": "-43.8"
    },
    "6year": {
      "change": "-50.0"
    },
    "23year": {
      "change": "-62.5"
    }
  },
  "grandLarcenyAuto": {
    "precinct": "10",
    "crime": {
      "name": "Grand Larceny Auto",
      "penal": "",
      "classification": "FELONY",
      "number": 115
    },
    "week": {
      "2015": "2",
      "2016": "0",
      "change": "-100.0"
    },
    "28day": {
      "2015": "4",
      "2016": "0",
      "change": "-100.0"
    },
    "year": {
      "2015": "2",
      "2016": "0",
      "change": "-100.0"
    },
    "2year": {
      "change": "-100.0"
    },
    "6year": {
      "change": "***.*"
    },
    "23year": {
      "change": "-100.0"
    }
  },
  "transit": {
    "precinct": "10",
    "crime": {
      "name": "Transit",
      "penal": "",
      "classification": "",
      "number": 141
    },
    "week": {
      "2015": "0",
      "2016": "0",
      "change": "***.*"
    },
    "28day": {
      "2015": "0",
      "2016": "2",
      "change": "***.*"
    },
    "year": {
      "2015": "0",
      "2016": "0",
      "change": "***.*"
    },
    "2year": {
      "change": "***.*"
    },
    "6year": {
      "change": "***.*"
    },
    "23year": {
      "change": "***.*"
    }
  },
  "housing": {
    "precinct": "10",
    "crime": {
      "name": "Housing",
      "penal": "",
      "classification": "",
      "number": 154
    },
    "week": {
      "2015": "0",
      "2016": "3",
      "change": "***.*"
    },
    "28day": {
      "2015": "2",
      "2016": "4",
      "change": "100.0"
    },
    "year": {
      "2015": "0",
      "2016": "3",
      "change": "***.*"
    },
    "2year": {
      "change": "200.0"
    },
    "6year": {
      "change": "200.0"
    },
    "23year": {
      "change": "***.*"
    }
  },
  "petitLarceny": {
    "precinct": "10",
    "crime": {
      "name": "Petit Larceny",
      "penal": "A",
      "classification": "MISDEMEANOR",
      "number": 167
    },
    "week": {
      "2015": "9",
      "2016": "19",
      "change": "111.1"
    },
    "28day": {
      "2015": "41",
      "2016": "62",
      "change": "51.2"
    },
    "year": {
      "2015": "18",
      "2016": "25",
      "change": "38.9"
    },
    "2year": {
      "change": "150.0"
    },
    "6year": {
      "change": "47.1"
    },
    "23year": {
      "change": "***.*"
    }
  },
  "misdAssault": {
    "precinct": "10",
    "crime": {
      "name": "Misdemeanor Assault",
      "penal": "A",
      "classification": "MISDEMEANOR",
      "number": 180
    },
    "week": {
      "2015": "1",
      "2016": "6",
      "change": "500.0"
    },
    "28day": {
      "2015": "15",
      "2016": "26",
      "change": "73.3"
    },
    "year": {
      "2015": "4",
      "2016": "9",
      "change": "125.0"
    },
    "2year": {
      "change": "0.0"
    },
    "6year": {
      "change": "0.0"
    },
    "23year": {
      "change": "***.*"
    }
  },
  "misdSexCrimes": {
    "precinct": "10",
    "crime": {
      "name": "Misdemeanor Sex Crimes",
      "penal": [
        "A",
        "B"
      ],
      "classification": "MISDEMEANOR",
      "number": 193
    },
    "week": {
      "2015": "0",
      "2016": "0",
      "change": "***.*"
    },
    "28day": {
      "2015": "2",
      "2016": "1",
      "change": "-50.0"
    },
    "year": {
      "2015": "0",
      "2016": "0",
      "change": "***.*"
    },
    "2year": {
      "change": "-100.0"
    },
    "6year": {
      "change": "-100.0"
    },
    "23year": {
      "change": "***.*"
    }
  },
  "shootingVic": {
    "precinct": "10",
    "crime": {
      "name": "Shooting with Victim",
      "penal": [
        "C",
        "D"
      ],
      "classification": "FELONY",
      "number": 206
    },
    "week": {
      "2015": "0",
      "2016": "0",
      "change": "***.*"
    },
    "28day": {
      "2015": "0",
      "2016": "0",
      "change": "***.*"
    },
    "year": {
      "2015": "0",
      "2016": "0",
      "change": "***.*"
    },
    "2year": {
      "change": "***.*"
    },
    "6year": {
      "change": "***.*"
    },
    "23year": {
      "change": "-100.0"
    }
  },
  "shootingInc": {
    "precinct": "10",
    "crime": {
      "name": "Shooting Incident",
      "penal": [
        "C",
        "D"
      ],
      "classification": "FELONY",
      "number": 219
    },
    "week": {
      "2015": "0",
      "2016": "0",
      "change": "***.*"
    },
    "28day": {
      "2015": "0",
      "2016": "0",
      "change": "***.*"
    },
    "year": {
      "2015": "0",
      "2016": "0",
      "change": "***.*"
    },
    "2year": {
      "change": "***.*"
    },
    "6year": {
      "change": "***.*"
    },
    "23year": {
      "change": "-100.0"
    }
  }
}